<?xml version="1.0"?>
<!DOCTYPE hibernate-mapping PUBLIC "-//Hibernate/Hibernate Mapping DTD 3.0//EN"
"http://hibernate.sourceforge.net/hibernate-mapping-3.0.dtd">
<!-- Generated Oct 9, 2014 5:46:57 PM by Hibernate Tools 3.4.0.CR1 -->
<hibernate-mapping>
	<class name="com.pft.string.service.api.common.bdo.UserSession"
		table="usersession" catalog="string_db">
		<id name="id" type="int">
			<column name="id" />
			<generator class="increment"/>
		</id>
		<property name="userSession" type="string">
			<column name="userSession" length="255" />
		</property>
		<property name="sessionTime" type="timestamp">
			<column name="sessionTime" length="23" />
		</property>
		<property name="userGuid" type="string">
			<column name="userGuid" length="255" />
		</property>
		<property name="username" type="string">
			<column name="username" length="255" />
		</property>		
	</class>
</hibernate-mapping>
